keepitrunning/__init__.py
keepitrunning/host.py
keepitrunning-1.0.5.dist-info/METADATA
keepitrunning-1.0.5.dist-info/WHEEL
keepitrunning-1.0.5.dist-info/top_level.txt
keepitrunning-1.0.5.dist-info/RECORD
