Metadata-Version: 2.1
Name: keepitrunning
Version: 1.0.5
Summary: A simple python library that makes your python website 24/7.
Home-page: https://github.com/jiroawesome/keepitrunning
Author: jiroawesome
License: UNKNOWN
Project-URL: Bug Tracker, https://github.com/jiroawesome/keepitrunning/issues
Platform: UNKNOWN
Classifier: Programming Language :: Python :: 3
Classifier: License :: OSI Approved :: MIT License
Classifier: Operating System :: OS Independent
Requires-Python: >=3.6
Requires-Dist: flask
